multiform_validator/__init__.py
multiform_validator/cnpjValidator.py
multiform_validator/cpfValidator.py
multiform_validator/getOnlyEmail.py
multiform_validator/identifyFlagCard.py
multiform_validator/isCreditCardValid.py
multiform_validator/isEmail.py
multiform_validator/isValidImage.py
multiform_validator/passwordStrengthTester.py
multiform_validator/validateBRPhoneNumber.py
multiform_validator-1.0.3.dist-info/LICENSE
multiform_validator-1.0.3.dist-info/METADATA
multiform_validator-1.0.3.dist-info/WHEEL
multiform_validator-1.0.3.dist-info/top_level.txt
multiform_validator-1.0.3.dist-info/RECORD
