Metadata-Version: 2.1
Name: multiform-validator
Version: 1.0.3
Summary: Multilingual library made for validation, various form fields, such as: email, cpf, cnpj, credit card, and much more.
Author: Gabriel Logan
Project-URL: Homepage, https://multiformvalidator.netlify.app/documentation
Project-URL: Bug Tracker, https://github.com/Multiform-Validator/python
Keywords: validator,multiform,validação,email-validator,image,multiform-validator,python,security,safe,pentest,security-tools,Validator,validate,cpf,cnpj,email validator,password,email,isEmail
Classifier: Programming Language :: Python :: 3
Classifier: License :: OSI Approved :: MIT License
Classifier: Operating System :: OS Independent
Requires-Python: >=3.1
License-File: LICENSE
